{
"1004":{
"name":"富贵初成",
"sheng_ming":720,
"gong_ji":15,
"fang_yu":6,
"bao_ji":9,
"kang_bao":12,
"ming_zhong":12,
"shan_bi":12,
"shang_mian":6
},
"1005":{
"name":"家财万贯",
"sheng_ming":1440,
"gong_ji":30,
"fang_yu":12,
"bao_ji":18,
"kang_bao":24,
"ming_zhong":24,
"shan_bi":24,
"shang_mian":12
},
"1006":{
"name":"富甲一方",
"sheng_ming":2160,
"gong_ji":45,
"fang_yu":18,
"bao_ji":27,
"kang_bao":36,
"ming_zhong":36,
"shan_bi":36,
"shang_mian":18
},
"1007":{
"name":"富可敌国",
"sheng_ming":2880,
"gong_ji":60,
"fang_yu":24,
"bao_ji":36,
"kang_bao":48,
"ming_zhong":48,
"shan_bi":48,
"shang_mian":24
},
"1008":{
"name":"超级富豪",
"sheng_ming":3600,
"gong_ji":75,
"fang_yu":30,
"bao_ji":45,
"kang_bao":60,
"ming_zhong":60,
"shan_bi":60,
"shang_mian":30
},
"1009":{
"name":"财倾天下",
"sheng_ming":4320,
"gong_ji":90,
"fang_yu":36,
"bao_ji":54,
"kang_bao":72,
"ming_zhong":72,
"shan_bi":72,
"shang_mian":36
},
"1101":{
"name":"初来乍到",
"sheng_ming":180,
"gong_ji":3,
"fang_yu":1,
"bao_ji":2,
"kang_bao":3,
"ming_zhong":3,
"shan_bi":3,
"shang_mian":1
},
"1103":{
"name":"魔兽小虾",
"sheng_ming":360,
"gong_ji":7,
"fang_yu":3,
"bao_ji":4,
"kang_bao":6,
"ming_zhong":6,
"shan_bi":6,
"shang_mian":3
},
"1104":{
"name":"魔兽战士",
"sheng_ming":720,
"gong_ji":15,
"fang_yu":6,
"bao_ji":9,
"kang_bao":12,
"ming_zhong":12,
"shan_bi":12,
"shang_mian":6
},
"1105":{
"name":"燃烧远征",
"sheng_ming":864,
"gong_ji":18,
"fang_yu":7,
"bao_ji":10,
"kang_bao":14,
"ming_zhong":14,
"shan_bi":14,
"shang_mian":7
},
"1106":{
"name":"银色勇士",
"sheng_ming":1152,
"gong_ji":24,
"fang_yu":9,
"bao_ji":14,
"kang_bao":19,
"ming_zhong":19,
"shan_bi":19,
"shang_mian":9
},
"1107":{
"name":"异界骑士",
"sheng_ming":1800,
"gong_ji":37,
"fang_yu":15,
"bao_ji":22,
"kang_bao":30,
"ming_zhong":30,
"shan_bi":30,
"shang_mian":15
},
"1108":{
"name":"全能之王",
"sheng_ming":2160,
"gong_ji":45,
"fang_yu":18,
"bao_ji":27,
"kang_bao":36,
"ming_zhong":36,
"shan_bi":36,
"shang_mian":18
},
"1109":{
"name":"无名小卒",
"sheng_ming":180,
"gong_ji":3,
"fang_yu":1,
"bao_ji":2,
"kang_bao":3,
"ming_zhong":3,
"shan_bi":3,
"shang_mian":1
},
"1111":{
"name":"小试牛刀",
"sheng_ming":360,
"gong_ji":7,
"fang_yu":3,
"bao_ji":4,
"kang_bao":6,
"ming_zhong":6,
"shan_bi":6,
"shang_mian":3
},
"1112":{
"name":"初露锋芒",
"sheng_ming":540,
"gong_ji":11,
"fang_yu":4,
"bao_ji":6,
"kang_bao":9,
"ming_zhong":9,
"shan_bi":9,
"shang_mian":4
},
"1113":{
"name":"泰坦使者",
"sheng_ming":720,
"gong_ji":15,
"fang_yu":6,
"bao_ji":9,
"kang_bao":12,
"ming_zhong":12,
"shan_bi":12,
"shang_mian":6
},
"1114":{
"name":"黎明之光",
"sheng_ming":900,
"gong_ji":18,
"fang_yu":7,
"bao_ji":11,
"kang_bao":15,
"ming_zhong":15,
"shan_bi":15,
"shang_mian":7
},
"1115":{
"name":"风暴末日",
"sheng_ming":1800,
"gong_ji":37,
"fang_yu":15,
"bao_ji":22,
"kang_bao":30,
"ming_zhong":30,
"shan_bi":30,
"shang_mian":15
},
"1116":{
"name":"末日审判",
"sheng_ming":2700,
"gong_ji":56,
"fang_yu":22,
"bao_ji":33,
"kang_bao":45,
"ming_zhong":45,
"shan_bi":45,
"shang_mian":22
},
"1117":{
"name":"黑暗大师",
"sheng_ming":3600,
"gong_ji":75,
"fang_yu":30,
"bao_ji":45,
"kang_bao":60,
"ming_zhong":60,
"shan_bi":60,
"shang_mian":30
},
"1118":{
"name":"破焰魔皇",
"sheng_ming":4500,
"gong_ji":93,
"fang_yu":37,
"bao_ji":56,
"kang_bao":75,
"ming_zhong":75,
"shan_bi":75,
"shang_mian":37
},
"1119":{
"name":"炎魔之王",
"sheng_ming":9000,
"gong_ji":187,
"fang_yu":75,
"bao_ji":112,
"kang_bao":150,
"ming_zhong":150,
"shan_bi":150,
"shang_mian":75
},
"1120":{
"name":"死亡之怒",
"sheng_ming":13320,
"gong_ji":277,
"fang_yu":111,
"bao_ji":166,
"kang_bao":222,
"ming_zhong":222,
"shan_bi":222,
"shang_mian":111
},
"1121":{
"name":"嗜血斗士",
"sheng_ming":18000,
"gong_ji":375,
"fang_yu":150,
"bao_ji":225,
"kang_bao":300,
"ming_zhong":300,
"shan_bi":300,
"shang_mian":150
}
}